{
  "folder": "hrezYkYmYgsGA3SJ",
  "name": "Ring of Ethereal Grasp",
  "type": "item",
  "_id": "CMJFasTX81lJqUUU",
  "img": "icons/equipment/finger/ring-band-skull-purple.webp",
  "system": {
    "cost": 1000,
    "weight": "normal",
    "description": "<p>Item Type: Ring</p><p>Grants the character 5 Aether that can only be spent on summoning Minions.</p><p></p>",
    "notes": "",
    "quantity": 1,
    "equippable": true
  },
  "effects": [],
  "flags": {},
  "_stats": {
    "compendiumSource": null,
    "duplicateSource": null,
    "exportSource": null,
    "coreVersion": "13.351",
    "systemId": "ker-nethalas",
    "systemVersion": "0.0.1",
    "createdTime": 1768738649768,
    "modifiedTime": 1768835921498,
    "lastModifiedBy": "xOca9XRwLgJMNAGV"
  },
  "ownership": {
    "default": 0
  },
  "sort": 0,
  "_key": "!items!CMJFasTX81lJqUUU"
}
